launch/Connection.py
launch/__init__.py
launch/download.py
launch/file.py
launch/find_version.py
launch/minecraft.py
minecraft_server/__init__.py
minecraft_server/file.py
minecraft_server/format.py
minecraft_server/server.py
minecraft_launcher_core-0.3.11.dist-info/LICENSE
minecraft_launcher_core-0.3.11.dist-info/METADATA
minecraft_launcher_core-0.3.11.dist-info/WHEEL
minecraft_launcher_core-0.3.11.dist-info/top_level.txt
minecraft_launcher_core-0.3.11.dist-info/RECORD
